tracenet/__init__.py
tracenet/python/__init__.py
tracenet/python/middleware.py
tracenet/typescript/README.md
tracenet/typescript/package-lock.json
tracenet/typescript/package.json
tracenet/typescript/tsconfig.json
tracenet/typescript/src/middleware.ts
tracenet-0.1.5.dist-info/METADATA
tracenet-0.1.5.dist-info/WHEEL
tracenet-0.1.5.dist-info/licenses/LICENSE
tracenet-0.1.5.dist-info/RECORD
