Metadata-Version: 2.4
Name: tracenet
Version: 0.1.5
Summary: Universal tracing middleware for LLM applications and AI agents with comprehensive observability
Project-URL: Homepage, https://github.com/stackgenhq/tracenet
Project-URL: Bug Tracker, https://github.com/stackgenhq/tracenet/issues
Author-email: Armaan Sayyad <armaans999@gmail.com>, Aarav Aggarwal <aarav.a0624@gmail.com>
License-File: LICENSE
Classifier: Development Status :: 4 - Beta
Classifier: Intended Audience :: Developers
Classifier: License :: OSI Approved :: MIT License
Classifier: Operating System :: OS Independent
Classifier: Programming Language :: Python :: 3
Classifier: Topic :: Software Development :: Libraries :: Python Modules
Classifier: Topic :: Software Development :: Testing
Requires-Python: >=3.8
Requires-Dist: langfuse==3.2.1
Requires-Dist: openinference-instrumentation-anthropic
Requires-Dist: openinference-instrumentation-langchain
Requires-Dist: openinference-instrumentation-llama-index
Requires-Dist: openinference-instrumentation-openai
Requires-Dist: openinference-instrumentation>=0.1.27
